z3c.etestbrowser-4.0-py3.9-nspkg.pth
z3c/etestbrowser/README.rst
z3c/etestbrowser/TODO.rst
z3c/etestbrowser/__init__.py
z3c/etestbrowser/browser.py
z3c/etestbrowser/empty.pt
z3c/etestbrowser/fake_index.pt
z3c/etestbrowser/ftesting.zcml
z3c/etestbrowser/funny.pt
z3c/etestbrowser/lxml.pt
z3c/etestbrowser/over_the_wire.rst
z3c/etestbrowser/testing.py
z3c/etestbrowser/tests.py
z3c.etestbrowser-4.0.dist-info/LICENSE.txt
z3c.etestbrowser-4.0.dist-info/METADATA
z3c.etestbrowser-4.0.dist-info/WHEEL
z3c.etestbrowser-4.0.dist-info/namespace_packages.txt
z3c.etestbrowser-4.0.dist-info/top_level.txt
z3c.etestbrowser-4.0.dist-info/RECORD
