Metadata-Version: 2.1
Name: z3c.etestbrowser
Version: 4.0
Summary: Extensions for zope.testbrowser
Home-page: https://github.com/zopefoundation/z3c.etestbrowser
Author: Christian Theune
Author-email: zope-dev@zope.dev
License: ZPL 2.1
Keywords: zope3 testbrowser lxml
Classifier: Development Status :: 5 - Production/Stable
Classifier: Environment :: Web Environment
Classifier: Intended Audience :: Developers
Classifier: License :: OSI Approved :: Zope Public License
Classifier: Programming Language :: Python :: 3
Classifier: Programming Language :: Python :: 3.7
Classifier: Programming Language :: Python :: 3.8
Classifier: Programming Language :: Python :: 3.9
Classifier: Programming Language :: Python :: 3.10
Classifier: Programming Language :: Python :: 3.11
Classifier: Natural Language :: English
Classifier: Operating System :: OS Independent
Classifier: Topic :: Internet :: WWW/HTTP
Classifier: Framework :: Zope :: 3
Requires-Python: >=3.7
License-File: LICENSE.txt
Requires-Dist: lxml (>=2.2)
Requires-Dist: setuptools
Requires-Dist: zope.deferredimport
Requires-Dist: zope.testbrowser (>=5.0)
Provides-Extra: test
Requires-Dist: zope.annotation ; extra == 'test'
Requires-Dist: zope.app.appsetup ; extra == 'test'
Requires-Dist: zope.app.publication ; extra == 'test'
Requires-Dist: zope.app.wsgi[testlayer] (>=4.0dev) ; extra == 'test'
Requires-Dist: zope.authentication ; extra == 'test'
Requires-Dist: zope.browserpage ; extra == 'test'
Requires-Dist: zope.component ; extra == 'test'
Requires-Dist: zope.container ; extra == 'test'
Requires-Dist: zope.location ; extra == 'test'
Requires-Dist: zope.principalregistry ; extra == 'test'
Requires-Dist: zope.publisher ; extra == 'test'
Requires-Dist: zope.security ; extra == 'test'
Requires-Dist: zope.securitypolicy ; extra == 'test'
Requires-Dist: zope.site ; extra == 'test'
Requires-Dist: zope.testbrowser[test] ; extra == 'test'
Requires-Dist: zope.testing ; extra == 'test'
Requires-Dist: zope.testrunner ; extra == 'test'
Requires-Dist: zope.traversing ; extra == 'test'
